klearn/__init__.py
klearn/bayes.py
klearn/kdtree.py
klearn/knn.py
klearn/sensor.py
klearn-0.0.3.dist-info/DESCRIPTION.rst
klearn-0.0.3.dist-info/METADATA
klearn-0.0.3.dist-info/RECORD
klearn-0.0.3.dist-info/WHEEL
klearn-0.0.3.dist-info/metadata.json
klearn-0.0.3.dist-info/top_level.txt
